pymatgen/analysis/diffusion/__init__.py
pymatgen/analysis/diffusion/analyzer.py
pymatgen/analysis/diffusion/aimd/__init__.py
pymatgen/analysis/diffusion/aimd/clustering.py
pymatgen/analysis/diffusion/aimd/pathway.py
pymatgen/analysis/diffusion/aimd/rdf.py
pymatgen/analysis/diffusion/aimd/van_hove.py
pymatgen/analysis/diffusion/neb/__init__.py
pymatgen/analysis/diffusion/neb/full_path_mapper.py
pymatgen/analysis/diffusion/neb/io.py
pymatgen/analysis/diffusion/neb/pathfinder.py
pymatgen/analysis/diffusion/neb/periodic_dijkstra.py
pymatgen/analysis/diffusion/utils/__init__.py
pymatgen/analysis/diffusion/utils/edge_data_from_sc.py
pymatgen/analysis/diffusion/utils/maggma.py
pymatgen/analysis/diffusion/utils/parse_entries.py
pymatgen/analysis/diffusion/utils/supercells.py
pymatgen_analysis_diffusion-2025.11.15.dist-info/licenses/LICENSE
pymatgen_analysis_diffusion-2025.11.15.dist-info/METADATA
pymatgen_analysis_diffusion-2025.11.15.dist-info/WHEEL
pymatgen_analysis_diffusion-2025.11.15.dist-info/top_level.txt
pymatgen_analysis_diffusion-2025.11.15.dist-info/RECORD
