Metadata-Version: 2.4
Name: pymatgen-analysis-diffusion
Version: 2025.11.15
Summary: Pymatgen add-on for diffusion analysis.
Author-email: Materials Virtual Lab <ongsp@ucsd.edu>
Maintainer-email: Shyue Ping Ong <ongsp@ucsd.edu>
License: BSD
Project-URL: Homepage, http://materialsvirtuallab.github.io/pymatgen-analysis-diffusion/
Project-URL: Documentation, http://materialsvirtuallab.github.io/pymatgen-analysis-diffusion/
Project-URL: Repository, https://github.com/materialsvirtuallab/pymatgen-analysis-diffusion
Project-URL: Issues, https://github.com/materialsvirtuallab/pymatgen-analysis-diffusion/issues
Project-URL: Pypi, https://pypi.org/project/pymatgen-analysis-diffusion
Keywords: ABINIT,analysis,crystal,diagrams,electronic,gaussian,materials,nwchem,phase,project,qchem,science,structure,VASP,diffusion,molecular dynamics,MD
Classifier: Programming Language :: Python :: 3
Classifier: Programming Language :: Python :: 3.10
Classifier: Programming Language :: Python :: 3.11
Classifier: Programming Language :: Python :: 3.12
Classifier: Development Status :: 4 - Beta
Classifier: Intended Audience :: Science/Research
Classifier: License :: OSI Approved :: BSD License
Classifier: Operating System :: OS Independent
Classifier: Topic :: Scientific/Engineering :: Information Analysis
Classifier: Topic :: Scientific/Engineering :: Physics
Classifier: Topic :: Scientific/Engineering :: Chemistry
Classifier: Topic :: Software Development :: Libraries :: Python Modules
Requires-Python: >=3.10
License-File: LICENSE
Requires-Dist: numpy<3.0,>=1.25.0
Requires-Dist: pymatgen>=2024.6.10
Requires-Dist: joblib
Requires-Dist: ase
Requires-Dist: seaborn
Provides-Extra: ci
Requires-Dist: pytest>=8; extra == "ci"
Requires-Dist: pytest-cov>=4; extra == "ci"
Requires-Dist: pytest-split>=0.8; extra == "ci"
Requires-Dist: maggma; extra == "ci"
Provides-Extra: docs
Requires-Dist: sphinx; extra == "docs"
Requires-Dist: sphinx_rtd_theme; extra == "docs"
Dynamic: license-file
